.gitignore
LICENSE
README.md
README.rst
setup.cfg
setup.py
cli_github/__init__.py
cli_github/mains.py
cli_github/utils.py
cli_github.egg-info/PKG-INFO
cli_github.egg-info/SOURCES.txt
cli_github.egg-info/dependency_links.txt
cli_github.egg-info/entry_points.txt
cli_github.egg-info/requires.txt
cli_github.egg-info/top_level.txt
images/gpl.png