Metadata-Version: 1.1
Name: cli-github
Version: 1.0.9
Summary: Github inside the Command Line
Home-page: https://github.com/harshasrinivas/cli-github/
Author: Harsha Srinivas
Author-email: 95harsha95@gmail.com
License: GPL v3.0
Keywords: github,CLI,github-within-CLI,python
Platform: UNKNOWN
Classifier: Operating System :: POSIX
Classifier: Environment :: Console
Classifier: License :: OSI Approved :: GNU General Public License v3 (GPLv3)
Classifier: Programming Language :: Python
Classifier: Programming Language :: Python :: 2
Classifier: Programming Language :: Python :: 2.7
Classifier: Programming Language :: Python :: 3
Classifier: Programming Language :: Python :: 3.2
Classifier: Programming Language :: Python :: 3.3
Classifier: Topic :: Utilities
Classifier: Topic :: Software Development :: Libraries :: Python Modules
Classifier: Topic :: Software Development :: User Interfaces
Classifier: Topic :: Software Development :: Version Control
